{"Ethiopia": ["Hispanic", "Cape Verde", "Russian", "Cameroon", "Ethiopian", "Afghanistan", "Crimean", "Ghanaian", "Eritrean", "Britain", "Eriteria", "Italy", "Syria", "Ukrainian", "African", "Iraq", "Norway", "Japanese", "Columbian", "Persian people", "Spain", "Ecuador", "Bengali", "Sierra Leon", "Saudi Arabian", "Arab", "Vietnam", "Somalia", "Jordan", "Iranian", "Lebanon", "Morocco", "Yemen", "Bangladesh", "Norweigan"], "Hispanic": ["Ethiopia", "Cape Verde", "Russian", "Cameroon", "Ethiopian", "Afghanistan", "Crimean", "Ghanaian", "Eritrean", "Britain", "Eriteria", "Italy", "Syria", "Ukrainian", "African", "Iraq", "Norway", "Japanese", "Columbian", "Persian people", "Spain", "Ecuador", "Bengali", "Sierra Leon", "Saudi Arabian", "Arab", "Vietnam", "Somalia", "Jordan", "Iranian", "Lebanon", "Morocco", "Yemen", "Bangladesh", "Norweigan"], "Cape Verde": ["Ethiopia", "Hispanic", "Russian", "Cameroon", "Ethiopian", "Afghanistan", "Crimean", "Ghanaian", "Eritrean", "Britain", "Eriteria", "Italy", "Syria", "Ukrainian", "African", "Iraq", "Norway", "Japanese", "Columbian", "Persian people", "Spain", "Ecuador", "Bengali", "Sierra Leon", "Saudi Arabian", "Arab", "Vietnam", "Somalia", "Jordan", "Iranian", "Lebanon", "Morocco", "Yemen", "Bangladesh", "Norweigan"], "Russian": ["Ethiopia", "Hispanic", "Cape Verde", "Cameroon", "Ethiopian", "Afghanistan", "Crimean", "Ghanaian", "Eritrean", "Britain", "Eriteria", "Italy", "Syria", "Ukrainian", "African", "Iraq", "Norway", "Japanese", "Columbian", "Persian people", "Spain", "Ecuador", "Bengali", "Sierra Leon", "Saudi Arabian", "Arab", "Vietnam", "Somalia", "Jordan", "Iranian", "Lebanon", "Morocco", "Yemen", "Bangladesh", "Norweigan"], "Cameroon": ["Ethiopia", "Hispanic", "Cape Verde", "Russian", "Ethiopian", "Afghanistan", "Crimean", "Ghanaian", "Eritrean", "Britain", "Eriteria", "Italy", "Syria", "Ukrainian", "African", "Iraq", "Norway", "Japanese", "Columbian", "Persian people", "Spain", "Ecuador", "Bengali", "Sierra Leon", "Saudi Arabian", "Arab", "Vietnam", "Somalia", "Jordan", "Iranian", "Lebanon", "Morocco", "Yemen", "Bangladesh", "Norweigan"], "Ethiopian": ["Ethiopia", "Hispanic", "Cape Verde", "Russian", "Cameroon", "Afghanistan", "Crimean", "Ghanaian", "Eritrean", "Britain", "Eriteria", "Italy", "Syria", "Ukrainian", "African", "Iraq", "Norway", "Japanese", "Columbian", "Persian people", "Spain", "Ecuador", "Bengali", "Sierra Leon", "Saudi Arabian", "Arab", "Vietnam", "Somalia", "Jordan", "Iranian", "Lebanon", "Morocco", "Yemen", "Bangladesh", "Norweigan"], "Afghanistan": ["Ethiopia", "Hispanic", "Cape Verde", "Russian", "Cameroon", "Ethiopian", "Crimean", "Ghanaian", "Eritrean", "Britain", "Eriteria", "Italy", "Syria", "Ukrainian", "African", "Iraq", "Norway", "Japanese", "Columbian", "Persian people", "Spain", "Ecuador", "Bengali", "Sierra Leon", "Saudi Arabian", "Arab", "Vietnam", "Somalia", "Jordan", "Iranian", "Lebanon", "Morocco", "Yemen", "Bangladesh", "Norweigan"], "Crimean": ["Ethiopia", "Hispanic", "Cape Verde", "Russian", "Cameroon", "Ethiopian", "Afghanistan", "Ghanaian", "Eritrean", "Britain", "Eriteria", "Italy", "Syria", "Ukrainian", "African", "Iraq", "Norway", "Japanese", "Columbian", "Persian people", "Spain", "Ecuador", "Bengali", "Sierra Leon", "Saudi Arabian", "Arab", "Vietnam", "Somalia", "Jordan", "Iranian", "Lebanon", "Morocco", "Yemen", "Bangladesh", "Norweigan"], "Ghanaian": ["Ethiopia", "Hispanic", "Cape Verde", "Russian", "Cameroon", "Ethiopian", "Afghanistan", "Crimean", "Eritrean", "Britain", "Eriteria", "Italy", "Syria", "Ukrainian", "African", "Iraq", "Norway", "Japanese", "Columbian", "Persian people", "Spain", "Ecuador", "Bengali", "Sierra Leon", "Saudi Arabian", "Arab", "Vietnam", "Somalia", "Jordan", "Iranian", "Lebanon", "Morocco", "Yemen", "Bangladesh", "Norweigan"], "Eritrean": ["Ethiopia", "Hispanic", "Cape Verde", "Russian", "Cameroon", "Ethiopian", "Afghanistan", "Crimean", "Ghanaian", "Britain", "Eriteria", "Italy", "Syria", "Ukrainian", "African", "Iraq", "Norway", "Japanese", "Columbian", "Persian people", "Spain", "Ecuador", "Bengali", "Sierra Leon", "Saudi Arabian", "Arab", "Vietnam", "Somalia", "Jordan", "Iranian", "Lebanon", "Morocco", "Yemen", "Bangladesh", "Norweigan"], "Britain": ["Ethiopia", "Hispanic", "Cape Verde", "Russian", "Cameroon", "Ethiopian", "Afghanistan", "Crimean", "Ghanaian", "Eritrean", "Eriteria", "Italy", "Syria", "Ukrainian", "African", "Iraq", "Norway", "Japanese", "Columbian", "Persian people", "Spain", "Ecuador", "Bengali", "Sierra Leon", "Saudi Arabian", "Arab", "Vietnam", "Somalia", "Jordan", "Iranian", "Lebanon", "Morocco", "Yemen", "Bangladesh", "Norweigan"], "Eriteria": ["Ethiopia", "Hispanic", "Cape Verde", "Russian", "Cameroon", "Ethiopian", "Afghanistan", "Crimean", "Ghanaian", "Eritrean", "Britain", "Italy", "Syria", "Ukrainian", "African", "Iraq", "Norway", "Japanese", "Columbian", "Persian people", "Spain", "Ecuador", "Bengali", "Sierra Leon", "Saudi Arabian", "Arab", "Vietnam", "Somalia", "Jordan", "Iranian", "Lebanon", "Morocco", "Yemen", "Bangladesh", "Norweigan"], "Italy": ["Ethiopia", "Hispanic", "Cape Verde", "Russian", "Cameroon", "Ethiopian", "Afghanistan", "Crimean", "Ghanaian", "Eritrean", "Britain", "Eriteria", "Syria", "Ukrainian", "African", "Iraq", "Norway", "Japanese", "Columbian", "Persian people", "Spain", "Ecuador", "Bengali", "Sierra Leon", "Saudi Arabian", "Arab", "Vietnam", "Somalia", "Jordan", "Iranian", "Lebanon", "Morocco", "Yemen", "Bangladesh", "Norweigan"], "Syria": ["Ethiopia", "Hispanic", "Cape Verde", "Russian", "Cameroon", "Ethiopian", "Afghanistan", "Crimean", "Ghanaian", "Eritrean", "Britain", "Eriteria", "Italy", "Ukrainian", "African", "Iraq", "Norway", "Japanese", "Columbian", "Persian people", "Spain", "Ecuador", "Bengali", "Sierra Leon", "Saudi Arabian", "Arab", "Vietnam", "Somalia", "Jordan", "Iranian", "Lebanon", "Morocco", "Yemen", "Bangladesh", "Norweigan"], "Ukrainian": ["Ethiopia", "Hispanic", "Cape Verde", "Russian", "Cameroon", "Ethiopian", "Afghanistan", "Crimean", "Ghanaian", "Eritrean", "Britain", "Eriteria", "Italy", "Syria", "African", "Iraq", "Norway", "Japanese", "Columbian", "Persian people", "Spain", "Ecuador", "Bengali", "Sierra Leon", "Saudi Arabian", "Arab", "Vietnam", "Somalia", "Jordan", "Iranian", "Lebanon", "Morocco", "Yemen", "Bangladesh", "Norweigan"], "African": ["Ethiopia", "Hispanic", "Cape Verde", "Russian", "Cameroon", "Ethiopian", "Afghanistan", "Crimean", "Ghanaian", "Eritrean", "Britain", "Eriteria", "Italy", "Syria", "Ukrainian", "Iraq", "Norway", "Japanese", "Columbian", "Persian people", "Spain", "Ecuador", "Bengali", "Sierra Leon", "Saudi Arabian", "Arab", "Vietnam", "Somalia", "Jordan", "Iranian", "Lebanon", "Morocco", "Yemen", "Bangladesh", "Norweigan"], "Iraq": ["Ethiopia", "Hispanic", "Cape Verde", "Russian", "Cameroon", "Ethiopian", "Afghanistan", "Crimean", "Ghanaian", "Eritrean", "Britain", "Eriteria", "Italy", "Syria", "Ukrainian", "African", "Norway", "Japanese", "Columbian", "Persian people", "Spain", "Ecuador", "Bengali", "Sierra Leon", "Saudi Arabian", "Arab", "Vietnam", "Somalia", "Jordan", "Iranian", "Lebanon", "Morocco", "Yemen", "Bangladesh", "Norweigan"], "Norway": ["Ethiopia", "Hispanic", "Cape Verde", "Russian", "Cameroon", "Ethiopian", "Afghanistan", "Crimean", "Ghanaian", "Eritrean", "Britain", "Eriteria", "Italy", "Syria", "Ukrainian", "African", "Iraq", "Japanese", "Columbian", "Persian people", "Spain", "Ecuador", "Bengali", "Sierra Leon", "Saudi Arabian", "Arab", "Vietnam", "Somalia", "Jordan", "Iranian", "Lebanon", "Morocco", "Yemen", "Bangladesh", "Norweigan"], "Japanese": ["Ethiopia", "Hispanic", "Cape Verde", "Russian", "Cameroon", "Ethiopian", "Afghanistan", "Crimean", "Ghanaian", "Eritrean", "Britain", "Eriteria", "Italy", "Syria", "Ukrainian", "African", "Iraq", "Norway", "Columbian", "Persian people", "Spain", "Ecuador", "Bengali", "Sierra Leon", "Saudi Arabian", "Arab", "Vietnam", "Somalia", "Jordan", "Iranian", "Lebanon", "Morocco", "Yemen", "Bangladesh", "Norweigan"], "Columbian": ["Ethiopia", "Hispanic", "Cape Verde", "Russian", "Cameroon", "Ethiopian", "Afghanistan", "Crimean", "Ghanaian", "Eritrean", "Britain", "Eriteria", "Italy", "Syria", "Ukrainian", "African", "Iraq", "Norway", "Japanese", "Persian people", "Spain", "Ecuador", "Bengali", "Sierra Leon", "Saudi Arabian", "Arab", "Vietnam", "Somalia", "Jordan", "Iranian", "Lebanon", "Morocco", "Yemen", "Bangladesh", "Norweigan"], "Persian people": ["Ethiopia", "Hispanic", "Cape Verde", "Russian", "Cameroon", "Ethiopian", "Afghanistan", "Crimean", "Ghanaian", "Eritrean", "Britain", "Eriteria", "Italy", "Syria", "Ukrainian", "African", "Iraq", "Norway", "Japanese", "Columbian", "Spain", "Ecuador", "Bengali", "Sierra Leon", "Saudi Arabian", "Arab", "Vietnam", "Somalia", "Jordan", "Iranian", "Lebanon", "Morocco", "Yemen", "Bangladesh", "Norweigan"], "Spain": ["Ethiopia", "Hispanic", "Cape Verde", "Russian", "Cameroon", "Ethiopian", "Afghanistan", "Crimean", "Ghanaian", "Eritrean", "Britain", "Eriteria", "Italy", "Syria", "Ukrainian", "African", "Iraq", "Norway", "Japanese", "Columbian", "Persian people", "Ecuador", "Bengali", "Sierra Leon", "Saudi Arabian", "Arab", "Vietnam", "Somalia", "Jordan", "Iranian", "Lebanon", "Morocco", "Yemen", "Bangladesh", "Norweigan"], "Ecuador": ["Ethiopia", "Hispanic", "Cape Verde", "Russian", "Cameroon", "Ethiopian", "Afghanistan", "Crimean", "Ghanaian", "Eritrean", "Britain", "Eriteria", "Italy", "Syria", "Ukrainian", "African", "Iraq", "Norway", "Japanese", "Columbian", "Persian people", "Spain", "Bengali", "Sierra Leon", "Saudi Arabian", "Arab", "Vietnam", "Somalia", "Jordan", "Iranian", "Lebanon", "Morocco", "Yemen", "Bangladesh", "Norweigan"], "Bengali": ["Ethiopia", "Hispanic", "Cape Verde", "Russian", "Cameroon", "Ethiopian", "Afghanistan", "Crimean", "Ghanaian", "Eritrean", "Britain", "Eriteria", "Italy", "Syria", "Ukrainian", "African", "Iraq", "Norway", "Japanese", "Columbian", "Persian people", "Spain", "Ecuador", "Sierra Leon", "Saudi Arabian", "Arab", "Vietnam", "Somalia", "Jordan", "Iranian", "Lebanon", "Morocco", "Yemen", "Bangladesh", "Norweigan"], "Sierra Leon": ["Ethiopia", "Hispanic", "Cape Verde", "Russian", "Cameroon", "Ethiopian", "Afghanistan", "Crimean", "Ghanaian", "Eritrean", "Britain", "Eriteria", "Italy", "Syria", "Ukrainian", "African", "Iraq", "Norway", "Japanese", "Columbian", "Persian people", "Spain", "Ecuador", "Bengali", "Saudi Arabian", "Arab", "Vietnam", "Somalia", "Jordan", "Iranian", "Lebanon", "Morocco", "Yemen", "Bangladesh", "Norweigan"], "Saudi Arabian": ["Ethiopia", "Hispanic", "Cape Verde", "Russian", "Cameroon", "Ethiopian", "Afghanistan", "Crimean", "Ghanaian", "Eritrean", "Britain", "Eriteria", "Italy", "Syria", "Ukrainian", "African", "Iraq", "Norway", "Japanese", "Columbian", "Persian people", "Spain", "Ecuador", "Bengali", "Sierra Leon", "Arab", "Vietnam", "Somalia", "Jordan", "Iranian", "Lebanon", "Morocco", "Yemen", "Bangladesh", "Norweigan"], "Arab": ["Ethiopia", "Hispanic", "Cape Verde", "Russian", "Cameroon", "Ethiopian", "Afghanistan", "Crimean", "Ghanaian", "Eritrean", "Britain", "Eriteria", "Italy", "Syria", "Ukrainian", "African", "Iraq", "Norway", "Japanese", "Columbian", "Persian people", "Spain", "Ecuador", "Bengali", "Sierra Leon", "Saudi Arabian", "Vietnam", "Somalia", "Jordan", "Iranian", "Lebanon", "Morocco", "Yemen", "Bangladesh", "Norweigan"], "Vietnam": ["Ethiopia", "Hispanic", "Cape Verde", "Russian", "Cameroon", "Ethiopian", "Afghanistan", "Crimean", "Ghanaian", "Eritrean", "Britain", "Eriteria", "Italy", "Syria", "Ukrainian", "African", "Iraq", "Norway", "Japanese", "Columbian", "Persian people", "Spain", "Ecuador", "Bengali", "Sierra Leon", "Saudi Arabian", "Arab", "Somalia", "Jordan", "Iranian", "Lebanon", "Morocco", "Yemen", "Bangladesh", "Norweigan"], "Somalia": ["Ethiopia", "Hispanic", "Cape Verde", "Russian", "Cameroon", "Ethiopian", "Afghanistan", "Crimean", "Ghanaian", "Eritrean", "Britain", "Eriteria", "Italy", "Syria", "Ukrainian", "African", "Iraq", "Norway", "Japanese", "Columbian", "Persian people", "Spain", "Ecuador", "Bengali", "Sierra Leon", "Saudi Arabian", "Arab", "Vietnam", "Jordan", "Iranian", "Lebanon", "Morocco", "Yemen", "Bangladesh", "Norweigan"], "Jordan": ["Ethiopia", "Hispanic", "Cape Verde", "Russian", "Cameroon", "Ethiopian", "Afghanistan", "Crimean", "Ghanaian", "Eritrean", "Britain", "Eriteria", "Italy", "Syria", "Ukrainian", "African", "Iraq", "Norway", "Japanese", "Columbian", "Persian people", "Spain", "Ecuador", "Bengali", "Sierra Leon", "Saudi Arabian", "Arab", "Vietnam", "Somalia", "Iranian", "Lebanon", "Morocco", "Yemen", "Bangladesh", "Norweigan"], "Iranian": ["Ethiopia", "Hispanic", "Cape Verde", "Russian", "Cameroon", "Ethiopian", "Afghanistan", "Crimean", "Ghanaian", "Eritrean", "Britain", "Eriteria", "Italy", "Syria", "Ukrainian", "African", "Iraq", "Norway", "Japanese", "Columbian", "Persian people", "Spain", "Ecuador", "Bengali", "Sierra Leon", "Saudi Arabian", "Arab", "Vietnam", "Somalia", "Jordan", "Lebanon", "Morocco", "Yemen", "Bangladesh", "Norweigan"], "Lebanon": ["Ethiopia", "Hispanic", "Cape Verde", "Russian", "Cameroon", "Ethiopian", "Afghanistan", "Crimean", "Ghanaian", "Eritrean", "Britain", "Eriteria", "Italy", "Syria", "Ukrainian", "African", "Iraq", "Norway", "Japanese", "Columbian", "Persian people", "Spain", "Ecuador", "Bengali", "Sierra Leon", "Saudi Arabian", "Arab", "Vietnam", "Somalia", "Jordan", "Iranian", "Morocco", "Yemen", "Bangladesh", "Norweigan"], "Morocco": ["Ethiopia", "Hispanic", "Cape Verde", "Russian", "Cameroon", "Ethiopian", "Afghanistan", "Crimean", "Ghanaian", "Eritrean", "Britain", "Eriteria", "Italy", "Syria", "Ukrainian", "African", "Iraq", "Norway", "Japanese", "Columbian", "Persian people", "Spain", "Ecuador", "Bengali", "Sierra Leon", "Saudi Arabian", "Arab", "Vietnam", "Somalia", "Jordan", "Iranian", "Lebanon", "Yemen", "Bangladesh", "Norweigan"], "Yemen": ["Ethiopia", "Hispanic", "Cape Verde", "Russian", "Cameroon", "Ethiopian", "Afghanistan", "Crimean", "Ghanaian", "Eritrean", "Britain", "Eriteria", "Italy", "Syria", "Ukrainian", "African", "Iraq", "Norway", "Japanese", "Columbian", "Persian people", "Spain", "Ecuador", "Bengali", "Sierra Leon", "Saudi Arabian", "Arab", "Vietnam", "Somalia", "Jordan", "Iranian", "Lebanon", "Morocco", "Bangladesh", "Norweigan"], "Bangladesh": ["Ethiopia", "Hispanic", "Cape Verde", "Russian", "Cameroon", "Ethiopian", "Afghanistan", "Crimean", "Ghanaian", "Eritrean", "Britain", "Eriteria", "Italy", "Syria", "Ukrainian", "African", "Iraq", "Norway", "Japanese", "Columbian", "Persian people", "Spain", "Ecuador", "Bengali", "Sierra Leon", "Saudi Arabian", "Arab", "Vietnam", "Somalia", "Jordan", "Iranian", "Lebanon", "Morocco", "Yemen", "Norweigan"], "Norweigan": ["Ethiopia", "Hispanic", "Cape Verde", "Russian", "Cameroon", "Ethiopian", "Afghanistan", "Crimean", "Ghanaian", "Eritrean", "Britain", "Eriteria", "Italy", "Syria", "Ukrainian", "African", "Iraq", "Norway", "Japanese", "Columbian", "Persian people", "Spain", "Ecuador", "Bengali", "Sierra Leon", "Saudi Arabian", "Arab", "Vietnam", "Somalia", "Jordan", "Iranian", "Lebanon", "Morocco", "Yemen", "Bangladesh"], "schoolgirl": ["mother", "herself", "male", "himself", "sister", "grandfather", "gentlemen", "mommy", "schoolboy"], "mother": ["schoolgirl", "herself", "male", "himself", "sister", "grandfather", "gentlemen", "mommy", "schoolboy"], "herself": ["schoolgirl", "mother", "male", "himself", "sister", "grandfather", "gentlemen", "mommy", "schoolboy"], "male": ["schoolgirl", "mother", "herself", "himself", "sister", "grandfather", "gentlemen", "mommy", "schoolboy"], "himself": ["schoolgirl", "mother", "herself", "male", "sister", "grandfather", "gentlemen", "mommy", "schoolboy"], "sister": ["schoolgirl", "mother", "herself", "male", "himself", "grandfather", "gentlemen", "mommy", "schoolboy"], "grandfather": ["schoolgirl", "mother", "herself", "male", "himself", "sister", "gentlemen", "mommy", "schoolboy"], "gentlemen": ["schoolgirl", "mother", "herself", "male", "himself", "sister", "grandfather", "mommy", "schoolboy"], "mommy": ["schoolgirl", "mother", "herself", "male", "himself", "sister", "grandfather", "gentlemen", "schoolboy"], "schoolboy": ["schoolgirl", "mother", "herself", "male", "himself", "sister", "grandfather", "gentlemen", "mommy"], "musician": ["physicist", "psychologist", "tailor", "mover", "civil servant", "chess player", "researcher", "producer", "entrepreneur", "performing artist", "commander", "mathematician", "policeman", "chemist", "guitarist", "manager", "software developer", "football player", "prisoner", "politician", "nurse", "assistant", "delivery man", "butcher", "historian", "prosecutor", "plumber", "bartender", "engineer"], "physicist": ["musician", "psychologist", "tailor", "mover", "civil servant", "chess player", "researcher", "producer", "entrepreneur", "performing artist", "commander", "mathematician", "policeman", "chemist", "guitarist", "manager", "software developer", "football player", "prisoner", "politician", "nurse", "assistant", "delivery man", "butcher", "historian", "prosecutor", "plumber", "bartender", "engineer"], "psychologist": ["musician", "physicist", "tailor", "mover", "civil servant", "chess player", "researcher", "producer", "entrepreneur", "performing artist", "commander", "mathematician", "policeman", "chemist", "guitarist", "manager", "software developer", "football player", "prisoner", "politician", "nurse", "assistant", "delivery man", "butcher", "historian", "prosecutor", "plumber", "bartender", "engineer"], "tailor": ["musician", "physicist", "psychologist", "mover", "civil servant", "chess player", "researcher", "producer", "entrepreneur", "performing artist", "commander", "mathematician", "policeman", "chemist", "guitarist", "manager", "software developer", "football player", "prisoner", "politician", "nurse", "assistant", "delivery man", "butcher", "historian", "prosecutor", "plumber", "bartender", "engineer"], "mover": ["musician", "physicist", "psychologist", "tailor", "civil servant", "chess player", "researcher", "producer", "entrepreneur", "performing artist", "commander", "mathematician", "policeman", "chemist", "guitarist", "manager", "software developer", "football player", "prisoner", "politician", "nurse", "assistant", "delivery man", "butcher", "historian", "prosecutor", "plumber", "bartender", "engineer"], "civil servant": ["musician", "physicist", "psychologist", "tailor", "mover", "chess player", "researcher", "producer", "entrepreneur", "performing artist", "commander", "mathematician", "policeman", "chemist", "guitarist", "manager", "software developer", "football player", "prisoner", "politician", "nurse", "assistant", "delivery man", "butcher", "historian", "prosecutor", "plumber", "bartender", "engineer"], "chess player": ["musician", "physicist", "psychologist", "tailor", "mover", "civil servant", "researcher", "producer", "entrepreneur", "performing artist", "commander", "mathematician", "policeman", "chemist", "guitarist", "manager", "software developer", "football player", "prisoner", "politician", "nurse", "assistant", "delivery man", "butcher", "historian", "prosecutor", "plumber", "bartender", "engineer"], "researcher": ["musician", "physicist", "psychologist", "tailor", "mover", "civil servant", "chess player", "producer", "entrepreneur", "performing artist", "commander", "mathematician", "policeman", "chemist", "guitarist", "manager", "software developer", "football player", "prisoner", "politician", "nurse", "assistant", "delivery man", "butcher", "historian", "prosecutor", "plumber", "bartender", "engineer"], "producer": ["musician", "physicist", "psychologist", "tailor", "mover", "civil servant", "chess player", "researcher", "entrepreneur", "performing artist", "commander", "mathematician", "policeman", "chemist", "guitarist", "manager", "software developer", "football player", "prisoner", "politician", "nurse", "assistant", "delivery man", "butcher", "historian", "prosecutor", "plumber", "bartender", "engineer"], "entrepreneur": ["musician", "physicist", "psychologist", "tailor", "mover", "civil servant", "chess player", "researcher", "producer", "performing artist", "commander", "mathematician", "policeman", "chemist", "guitarist", "manager", "software developer", "football player", "prisoner", "politician", "nurse", "assistant", "delivery man", "butcher", "historian", "prosecutor", "plumber", "bartender", "engineer"], "performing artist": ["musician", "physicist", "psychologist", "tailor", "mover", "civil servant", "chess player", "researcher", "producer", "entrepreneur", "commander", "mathematician", "policeman", "chemist", "guitarist", "manager", "software developer", "football player", "prisoner", "politician", "nurse", "assistant", "delivery man", "butcher", "historian", "prosecutor", "plumber", "bartender", "engineer"], "commander": ["musician", "physicist", "psychologist", "tailor", "mover", "civil servant", "chess player", "researcher", "producer", "entrepreneur", "performing artist", "mathematician", "policeman", "chemist", "guitarist", "manager", "software developer", "football player", "prisoner", "politician", "nurse", "assistant", "delivery man", "butcher", "historian", "prosecutor", "plumber", "bartender", "engineer"], "mathematician": ["musician", "physicist", "psychologist", "tailor", "mover", "civil servant", "chess player", "researcher", "producer", "entrepreneur", "performing artist", "commander", "policeman", "chemist", "guitarist", "manager", "software developer", "football player", "prisoner", "politician", "nurse", "assistant", "delivery man", "butcher", "historian", "prosecutor", "plumber", "bartender", "engineer"], "policeman": ["musician", "physicist", "psychologist", "tailor", "mover", "civil servant", "chess player", "researcher", "producer", "entrepreneur", "performing artist", "commander", "mathematician", "chemist", "guitarist", "manager", "software developer", "football player", "prisoner", "politician", "nurse", "assistant", "delivery man", "butcher", "historian", "prosecutor", "plumber", "bartender", "engineer"], "chemist": ["musician", "physicist", "psychologist", "tailor", "mover", "civil servant", "chess player", "researcher", "producer", "entrepreneur", "performing artist", "commander", "mathematician", "policeman", "guitarist", "manager", "software developer", "football player", "prisoner", "politician", "nurse", "assistant", "delivery man", "butcher", "historian", "prosecutor", "plumber", "bartender", "engineer"], "guitarist": ["musician", "physicist", "psychologist", "tailor", "mover", "civil servant", "chess player", "researcher", "producer", "entrepreneur", "performing artist", "commander", "mathematician", "policeman", "chemist", "manager", "software developer", "football player", "prisoner", "politician", "nurse", "assistant", "delivery man", "butcher", "historian", "prosecutor", "plumber", "bartender", "engineer"], "manager": ["musician", "physicist", "psychologist", "tailor", "mover", "civil servant", "chess player", "researcher", "producer", "entrepreneur", "performing artist", "commander", "mathematician", "policeman", "chemist", "guitarist", "software developer", "football player", "prisoner", "politician", "nurse", "assistant", "delivery man", "butcher", "historian", "prosecutor", "plumber", "bartender", "engineer"], "software developer": ["musician", "physicist", "psychologist", "tailor", "mover", "civil servant", "chess player", "researcher", "producer", "entrepreneur", "performing artist", "commander", "mathematician", "policeman", "chemist", "guitarist", "manager", "football player", "prisoner", "politician", "nurse", "assistant", "delivery man", "butcher", "historian", "prosecutor", "plumber", "bartender", "engineer"], "football player": ["musician", "physicist", "psychologist", "tailor", "mover", "civil servant", "chess player", "researcher", "producer", "entrepreneur", "performing artist", "commander", "mathematician", "policeman", "chemist", "guitarist", "manager", "software developer", "prisoner", "politician", "nurse", "assistant", "delivery man", "butcher", "historian", "prosecutor", "plumber", "bartender", "engineer"], "prisoner": ["musician", "physicist", "psychologist", "tailor", "mover", "civil servant", "chess player", "researcher", "producer", "entrepreneur", "performing artist", "commander", "mathematician", "policeman", "chemist", "guitarist", "manager", "software developer", "football player", "politician", "nurse", "assistant", "delivery man", "butcher", "historian", "prosecutor", "plumber", "bartender", "engineer"], "politician": ["musician", "physicist", "psychologist", "tailor", "mover", "civil servant", "chess player", "researcher", "producer", "entrepreneur", "performing artist", "commander", "mathematician", "policeman", "chemist", "guitarist", "manager", "software developer", "football player", "prisoner", "nurse", "assistant", "delivery man", "butcher", "historian", "prosecutor", "plumber", "bartender", "engineer"], "nurse": ["musician", "physicist", "psychologist", "tailor", "mover", "civil servant", "chess player", "researcher", "producer", "entrepreneur", "performing artist", "commander", "mathematician", "policeman", "chemist", "guitarist", "manager", "software developer", "football player", "prisoner", "politician", "assistant", "delivery man", "butcher", "historian", "prosecutor", "plumber", "bartender", "engineer"], "assistant": ["musician", "physicist", "psychologist", "tailor", "mover", "civil servant", "chess player", "researcher", "producer", "entrepreneur", "performing artist", "commander", "mathematician", "policeman", "chemist", "guitarist", "manager", "software developer", "football player", "prisoner", "politician", "nurse", "delivery man", "butcher", "historian", "prosecutor", "plumber", "bartender", "engineer"], "delivery man": ["musician", "physicist", "psychologist", "tailor", "mover", "civil servant", "chess player", "researcher", "producer", "entrepreneur", "performing artist", "commander", "mathematician", "policeman", "chemist", "guitarist", "manager", "software developer", "football player", "prisoner", "politician", "nurse", "assistant", "butcher", "historian", "prosecutor", "plumber", "bartender", "engineer"], "butcher": ["musician", "physicist", "psychologist", "tailor", "mover", "civil servant", "chess player", "researcher", "producer", "entrepreneur", "performing artist", "commander", "mathematician", "policeman", "chemist", "guitarist", "manager", "software developer", "football player", "prisoner", "politician", "nurse", "assistant", "delivery man", "historian", "prosecutor", "plumber", "bartender", "engineer"], "historian": ["musician", "physicist", "psychologist", "tailor", "mover", "civil servant", "chess player", "researcher", "producer", "entrepreneur", "performing artist", "commander", "mathematician", "policeman", "chemist", "guitarist", "manager", "software developer", "football player", "prisoner", "politician", "nurse", "assistant", "delivery man", "butcher", "prosecutor", "plumber", "bartender", "engineer"], "prosecutor": ["musician", "physicist", "psychologist", "tailor", "mover", "civil servant", "chess player", "researcher", "producer", "entrepreneur", "performing artist", "commander", "mathematician", "policeman", "chemist", "guitarist", "manager", "software developer", "football player", "prisoner", "politician", "nurse", "assistant", "delivery man", "butcher", "historian", "plumber", "bartender", "engineer"], "plumber": ["musician", "physicist", "psychologist", "tailor", "mover", "civil servant", "chess player", "researcher", "producer", "entrepreneur", "performing artist", "commander", "mathematician", "policeman", "chemist", "guitarist", "manager", "software developer", "football player", "prisoner", "politician", "nurse", "assistant", "delivery man", "butcher", "historian", "prosecutor", "bartender", "engineer"], "bartender": ["musician", "physicist", "psychologist", "tailor", "mover", "civil servant", "chess player", "researcher", "producer", "entrepreneur", "performing artist", "commander", "mathematician", "policeman", "chemist", "guitarist", "manager", "software developer", "football player", "prisoner", "politician", "nurse", "assistant", "delivery man", "butcher", "historian", "prosecutor", "plumber", "engineer"], "engineer": ["musician", "physicist", "psychologist", "tailor", "mover", "civil servant", "chess player", "researcher", "producer", "entrepreneur", "performing artist", "commander", "mathematician", "policeman", "chemist", "guitarist", "manager", "software developer", "football player", "prisoner", "politician", "nurse", "assistant", "delivery man", "butcher", "historian", "prosecutor", "plumber", "bartender"], "Muslim": ["Bible", "Brahmin"], "Bible": ["Muslim", "Brahmin"], "Brahmin": ["Muslim", "Bible"]}